dsnd_dist/Binomialdistribution.py
dsnd_dist/Gaussiandistribution.py
dsnd_dist/Generaldistribution.py
dsnd_dist/__init__.py
dsnd_dist-0.1.dist-info/METADATA
dsnd_dist-0.1.dist-info/WHEEL
dsnd_dist-0.1.dist-info/top_level.txt
dsnd_dist-0.1.dist-info/RECORD
