Metadata-Version: 2.1
Name: dsnd_dist
Version: 0.1
Summary: Gaussian and Binomial distributions
Home-page: UNKNOWN
Author: jfpinedap
Author-email: jfpinedap@gmail.com
License: UNKNOWN
Platform: UNKNOWN
